{
  "applications": "*",
  "changelogDate": "20220302074026",
  "dto": "mapstruct",
  "embedded": false,
  "entityTableName": "tranfer_details_approvals",
  "fields": [
    {
      "fieldName": "approvalDate",
      "fieldType": "Instant"
    },
    {
      "fieldName": "qtyRequested",
      "fieldType": "Double"
    },
    {
      "fieldName": "qtyApproved",
      "fieldType": "Double"
    },
    {
      "fieldName": "comment",
      "fieldType": "String"
    },
    {
      "fieldName": "freeField1",
      "fieldType": "String"
    },
    {
      "fieldName": "freeField2",
      "fieldType": "String"
    },
    {
      "fieldName": "lastModified",
      "fieldType": "Instant"
    },
    {
      "fieldName": "lastModifiedBy",
      "fieldType": "String"
    },
    {
      "fieldName": "isDeleted",
      "fieldType": "Boolean"
    },
    {
      "fieldName": "isActive",
      "fieldType": "Boolean"
    }
  ],
  "fluentMethods": true,
  "jpaMetamodelFiltering": true,
  "name": "TranferDetailsApprovals",
  "pagination": "pagination",
  "readOnly": false,
  "relationships": [
    {
      "otherEntityName": "transfer",
      "otherEntityRelationshipName": "tranferDetailsApprovals",
      "relationshipName": "transfer",
      "relationshipType": "many-to-one"
    }
  ],
  "service": "serviceClass"
}
